qapi/__init__.py
qapi/querystring_builder.py
qapi/action/__init__.py
qapi/action/group.py
qapi/action/order.py
qapi/action/where.py
qapi/dialect/__init__.py
qapi/dialect/sqlalchemy.py
qapi/state_machine/__init__.py
qapi/state_machine/querystring.py
qapi-0.0.2.dist-info/METADATA
qapi-0.0.2.dist-info/WHEEL
qapi-0.0.2.dist-info/top_level.txt
qapi-0.0.2.dist-info/RECORD
