Metadata-Version: 2.1
Name: qapi
Version: 0.0.2
Summary: QAPI - API query language
Home-page: https://github.com/Zeon-Code/qapi
Author: Diego Peres
Author-email: speres.diego@gmail.com
License: UNKNOWN
Keywords: qapi,API,Query Language
Platform: UNKNOWN
Classifier: Programming Language :: Python :: 3
Requires-Python: >=3.6
Requires-Dist: sqlalchemy
Provides-Extra: test
Requires-Dist: pytest ; extra == 'test'
